gaugan/__init__.py
gaugan-1.dist-info/LICENSE
gaugan-1.dist-info/METADATA
gaugan-1.dist-info/WHEEL
gaugan-1.dist-info/top_level.txt
gaugan-1.dist-info/RECORD
