Metadata-Version: 2.1
Name: gaugan
Version: 1
Summary: An interface for NVIDIA's gauGAN project that turns crude drawings into realistic images using AI.
Home-page: https://github.com/erikKeresztes/gaugan.py
Author: Erik Keresztes
Author-email: erik@erik.cash
License: UNKNOWN
Platform: UNKNOWN
Classifier: Programming Language :: Python :: 3
Classifier: License :: OSI Approved :: The Unlicense (Unlicense)
Classifier: Operating System :: OS Independent
Requires-Python: >=3
